angutils/__init__.py
angutils/angutils.py
angutils-1.0.0.dist-info/licenses/LICENSE
angutils-1.0.0.dist-info/METADATA
angutils-1.0.0.dist-info/WHEEL
angutils-1.0.0.dist-info/top_level.txt
angutils-1.0.0.dist-info/RECORD
